easyrunner/.server-config/infra/authelia/configuration.template.yml
easyrunner/.server-config/infra/authelia/configuration.yml
easyrunner/.server-config/infra/authelia/local-dns-setup.sh
easyrunner/.server-config/infra/authelia/notification.txt
easyrunner/.server-config/infra/authelia/users_database.yaml
easyrunner/.server-config/infra/caddy/Caddyfile
easyrunner/.server-config/infra/caddy/Caddyfile with authcrunch
easyrunner/.server-config/infra/caddy/Caddyfile with ldap
easyrunner/.server-config/infra/docker-compose/.env.dev
easyrunner/.server-config/infra/docker-compose/.env.prod
easyrunner/.server-config/infra/docker-compose/docker-compose-host.yaml
easyrunner/.templates/docker-compose/docker-compose-app.yaml
easyrunner/.templates/docker-compose/docker-compose-helloworld.yaml
easyrunner/README.md
easyrunner/__init__.py
easyrunner/easyrunner_build.py
easyrunner/poetry.lock
easyrunner/pyproject.toml
easyrunner/pytest.ini
easyrunner/source/cloud_providers/__init__.py
easyrunner/source/cloud_providers/cloud_provider_base.py
easyrunner/source/cloud_providers/cloud_providers.py
easyrunner/source/cloud_providers/hetzner_provider.py
easyrunner/source/command_executor.py
easyrunner/source/command_executor_local.py
easyrunner/source/commands/__init__.py
easyrunner/source/commands/base/__init__.py
easyrunner/source/commands/base/archive_commands.py
easyrunner/source/commands/base/caddy_api_curl_commands.py
easyrunner/source/commands/base/caddy_commands.py
easyrunner/source/commands/base/command_base.py
easyrunner/source/commands/base/curl_commands.py
easyrunner/source/commands/base/dir_commands.py
easyrunner/source/commands/base/docker_compose_commands.py
easyrunner/source/commands/base/file_commands.py
easyrunner/source/commands/base/git_commands.py
easyrunner/source/commands/base/ip_tables_commands.py
easyrunner/source/commands/base/ip_tables_persistent_commands.py
easyrunner/source/commands/base/null_command.py
easyrunner_cli-0.0.7.dist-info/METADATA
easyrunner_cli-0.0.7.dist-info/WHEEL
easyrunner_cli-0.0.7.dist-info/entry_points.txt
easyrunner_cli-0.0.7.dist-info/RECORD
