Metadata-Version: 2.4
Name: easyrunner_cli
Version: 0.0.7
Summary: EasyRunner CLI.
Author: Janaka Abeywardhana
Author-email: janaka@easyrunner.xyz
Requires-Python: >=3.13,<4.0
Classifier: Programming Language :: Python :: 3
Classifier: Programming Language :: Python :: 3.13
Classifier: Programming Language :: Python :: 3.14
Requires-Dist: cryptography (>=44.0.0,<45.0.0)
Requires-Dist: fabric (>=3.2.2,<4.0.0)
Requires-Dist: keyring (>=25.6.0,<26.0.0)
Requires-Dist: pulumi (>=3.185.0,<4.0.0)
Requires-Dist: pulumi-aws (>=7.1.0,<8.0.0)
Requires-Dist: pulumi-hcloud (>=1.23.1,<2.0.0)
Requires-Dist: pyjwt (>=2.9.0,<3.0.0)
Requires-Dist: pyobjc-framework-Security (>=10.3.1,<11.0.0) ; sys_platform == "darwin"
Requires-Dist: pyyaml (>=6.0.2,<7.0.0)
Requires-Dist: requests (>=2.32.5,<3.0.0)
Requires-Dist: rich (>=13.9.4,<14.0.0)
Requires-Dist: typer (>=0.15.1,<0.16.0)
Requires-Dist: typing-extensions (>=4.12.2,<5.0.0)
Project-URL: Homepage, https://easyrunner.xyz
Project-URL: Repository, https://github.com/janaka/easyrunner
